CHANGES.txt
CONTRIBUTORS.txt
MANIFEST.in
README.txt
setup.py
cs/__init__.py
cs.accreditedfile.egg-info/PKG-INFO
cs.accreditedfile.egg-info/SOURCES.txt
cs.accreditedfile.egg-info/dependency_links.txt
cs.accreditedfile.egg-info/entry_points.txt
cs.accreditedfile.egg-info/namespace_packages.txt
cs.accreditedfile.egg-info/not-zip-safe
cs.accreditedfile.egg-info/paster_plugins.txt
cs.accreditedfile.egg-info/requires.txt
cs.accreditedfile.egg-info/top_level.txt
cs/accreditedfile/README.txt
cs/accreditedfile/__init__.py
cs/accreditedfile/config.py
cs/accreditedfile/configure.zcml
cs/accreditedfile/future.py
cs/accreditedfile/helpers.py
cs/accreditedfile/rebuild_i18n.sh
cs/accreditedfile/subscriber.py
cs/accreditedfile/tests.py
cs/accreditedfile/browser/__init__.py
cs/accreditedfile/browser/accreditation.py
cs/accreditedfile/browser/accreditedfileview.pt
cs/accreditedfile/browser/accreditedfileview.py
cs/accreditedfile/browser/configure.zcml
cs/accreditedfile/content/__init__.py
cs/accreditedfile/content/accreditedfile.py
cs/accreditedfile/content/configure.zcml
cs/accreditedfile/interfaces/__init__.py
cs/accreditedfile/interfaces/accreditedfile.py
cs/accreditedfile/locales/cs.accreditedfile-manual.pot
cs/accreditedfile/locales/cs.accreditedfile.pot
cs/accreditedfile/locales/es/LC_MESSAGES/cs.accreditedfile.po
cs/accreditedfile/locales/eu/LC_MESSAGES/cs.accreditedfile.po
cs/accreditedfile/profiles/default/actions.xml
cs/accreditedfile/profiles/default/factorytool.xml
cs/accreditedfile/profiles/default/metadata.xml
cs/accreditedfile/profiles/default/propertiestool.xml
cs/accreditedfile/profiles/default/registry.xml
cs/accreditedfile/profiles/default/rolemap.xml
cs/accreditedfile/profiles/default/types.xml
cs/accreditedfile/profiles/default/workflows.xml
cs/accreditedfile/profiles/default/types/AccreditedFile.xml
cs/accreditedfile/tests/__init__.py
cs/accreditedfile/tests/base.py
cs/accreditedfile/tests/test_doctest.py
docs/HISTORY.txt
docs/INSTALL.txt
docs/LICENSE.GPL
docs/LICENSE.txt