Metadata-Version: 1.1
Name: cs.accreditedfile
Version: 1.5
Summary: Files that get published in a website and the publication is accredited by Izenpe (http://www.izenpe.com)
Home-page: http://www.codesyntax.com/products/cs.accreditedfile
Author: Mikel Larreategi
Author-email: mlarreategi@codesyntax.com
License: GPL
Platform: UNKNOWN
Classifier: Framework :: Plone
Classifier: Intended Audience :: Developers
Classifier: License :: OSI Approved :: GNU General Public License (GPL)
